{
  "/_not-found/page": "app/_not-found/page.js",
  "/access-pending/page": "app/access-pending/page.js",
  "/get-started/page": "app/get-started/page.js",
  "/how-it-works/page": "app/how-it-works/page.js",
  "/onboarding/business/branch/page": "app/onboarding/business/branch/page.js",
  "/onboarding/business/category/page": "app/onboarding/business/category/page.js",
  "/onboarding/business/account/page": "app/onboarding/business/account/page.js",
  "/onboarding/business/details/page": "app/onboarding/business/details/page.js",
  "/onboarding/business/subtype/page": "app/onboarding/business/subtype/page.js",
  "/onboarding/business/review/page": "app/onboarding/business/review/page.js",
  "/onboarding/provider/account/page": "app/onboarding/provider/account/page.js",
  "/onboarding/provider/profile/page": "app/onboarding/provider/profile/page.js",
  "/onboarding/provider/review/page": "app/onboarding/provider/review/page.js",
  "/onboarding/provider/type/page": "app/onboarding/provider/type/page.js",
  "/page": "app/page.js",
  "/onboarding/provider/join/page": "app/onboarding/provider/join/page.js",
  "/t/[slug]/page": "app/t/[slug]/page.js",
  "/(shell)/dashboard/analytics/page": "app/(shell)/dashboard/analytics/page.js",
  "/(auth)/login/page": "app/(auth)/login/page.js",
  "/(auth)/register/page": "app/(auth)/register/page.js",
  "/(shell)/dashboard/beauty-grooming/ops/page": "app/(shell)/dashboard/beauty-grooming/ops/page.js",
  "/(shell)/dashboard/audit-logs/page": "app/(shell)/dashboard/audit-logs/page.js",
  "/(shell)/dashboard/audit-logs/[id]/page": "app/(shell)/dashboard/audit-logs/[id]/page.js",
  "/(shell)/dashboard/beauty-grooming/catalog/page": "app/(shell)/dashboard/beauty-grooming/catalog/page.js",
  "/(shell)/dashboard/beauty-grooming/page": "app/(shell)/dashboard/beauty-grooming/page.js",
  "/(shell)/dashboard/conversations/page": "app/(shell)/dashboard/conversations/page.js",
  "/(shell)/dashboard/food-dining/menu/page": "app/(shell)/dashboard/food-dining/menu/page.js",
  "/(auth)/forgot-password/page": "app/(auth)/forgot-password/page.js",
  "/(shell)/dashboard/beauty-grooming/specializations/page": "app/(shell)/dashboard/beauty-grooming/specializations/page.js",
  "/(shell)/dashboard/food-dining/ops/page": "app/(shell)/dashboard/food-dining/ops/page.js",
  "/(shell)/dashboard/food-dining/page": "app/(shell)/dashboard/food-dining/page.js",
  "/(shell)/dashboard/food-dining/tables/page": "app/(shell)/dashboard/food-dining/tables/page.js",
  "/(shell)/dashboard/payments/page": "app/(shell)/dashboard/payments/page.js",
  "/(shell)/dashboard/operations/page": "app/(shell)/dashboard/operations/page.js",
  "/(shell)/dashboard/qr/page": "app/(shell)/dashboard/qr/page.js",
  "/(shell)/dashboard/page": "app/(shell)/dashboard/page.js",
  "/(shell)/dashboard/reconciliation/page": "app/(shell)/dashboard/reconciliation/page.js",
  "/(shell)/dashboard/settings/branch/page": "app/(shell)/dashboard/settings/branch/page.js",
  "/(shell)/dashboard/settings/business/page": "app/(shell)/dashboard/settings/business/page.js",
  "/(shell)/dashboard/settings/landing/page": "app/(shell)/dashboard/settings/landing/page.js",
  "/(shell)/dashboard/settings/categories/page": "app/(shell)/dashboard/settings/categories/page.js",
  "/(shell)/dashboard/settings/page": "app/(shell)/dashboard/settings/page.js",
  "/(shell)/dashboard/settings/profile/page": "app/(shell)/dashboard/settings/profile/page.js",
  "/(shell)/dashboard/staff/[id]/page": "app/(shell)/dashboard/staff/[id]/page.js",
  "/(shell)/dashboard/beauty-grooming/stations/page": "app/(shell)/dashboard/beauty-grooming/stations/page.js",
  "/(shell)/dashboard/settings/payments/page": "app/(shell)/dashboard/settings/payments/page.js",
  "/(shell)/dashboard/staff/link/page": "app/(shell)/dashboard/staff/link/page.js",
  "/admin/approvals/page": "app/admin/approvals/page.js",
  "/admin/audit-risk/page": "app/admin/audit-risk/page.js",
  "/(shell)/dashboard/statements/page": "app/(shell)/dashboard/statements/page.js",
  "/(shell)/dashboard/staff/page": "app/(shell)/dashboard/staff/page.js",
  "/admin/category-adoption/page": "app/admin/category-adoption/page.js",
  "/admin/impersonation/page": "app/admin/impersonation/page.js",
  "/admin/page": "app/admin/page.js",
  "/admin/orders/page": "app/admin/orders/page.js",
  "/admin/payments-health/page": "app/admin/payments-health/page.js",
  "/admin/reconciliation/page": "app/admin/reconciliation/page.js",
  "/admin/system/page": "app/admin/system/page.js",
  "/admin/tenants/[id]/page": "app/admin/tenants/[id]/page.js",
  "/admin/tenants/page": "app/admin/tenants/page.js",
  "/provider/page": "app/provider/page.js",
  "/provider/requests/page": "app/provider/requests/page.js",
  "/provider/ratings/page": "app/provider/ratings/page.js",
  "/provider/settings/page": "app/provider/settings/page.js",
  "/admin/users/page": "app/admin/users/page.js",
  "/provider/assignments/page": "app/provider/assignments/page.js",
  "/provider/tips/page": "app/provider/tips/page.js",
  "/provider/profile/page": "app/provider/profile/page.js"
}